[

    {
        "id":100,
        "date":"12/12/2022",
        "vendorname":"Anna",
        "total":"$1200"
    },
    
    {
    "id":101,
        "date":"22/12/2022",
        "vendorname":"jack",
        "total":"$2500"
    },

    {
        "id":102,
        "date":"30/12/2022",
        "vendorname":"Rosy",
        "total":"$7800"
    },

    {
        "id":103,
        "date":"1/01/2023",
        "vendorname":"Antony",
        "total":"$1800"
    },

    {
        "id":104,
        "date":"12/01/2022",
        "vendorname":"Ammy",
        "total":"$3400"
    },

    {
        "id":105,
        "date":"28/01/2023",
        "vendorname":"Nick",
        "total":"$9000"
    },

    {
        "id":106,
        "date":"08/02/2023",
        "vendorname":"nova",
        "total":"$4700"
    },

    {
        "id":107,
        "date":"28/02/2023",
        "vendorname":"Satya",
        "total":"$4680"
    },

    {
        "id":108,
        "date":"12/03/2023",
        "vendorname":"kevin",
        "total":"$5430"
    },

    {
        "id":109,
        "date":"30/03/2023",
        "vendorname":"Ana",
        "total":"$8600"
    },

    {
        "id":110,
        "date":"13/04/2023",
        "vendorname":"Tiyana",
        "total":"$7890"
    }
]